pyMPC/__init__.py
pyMPC/kalman.py
pyMPC/mpc.py
pyMPC/mpc_no_slack.py
python_mpc-0.1.1.dist-info/LICENSE.md
python_mpc-0.1.1.dist-info/METADATA
python_mpc-0.1.1.dist-info/WHEEL
python_mpc-0.1.1.dist-info/top_level.txt
python_mpc-0.1.1.dist-info/RECORD
